{
  "id": "4cg53-forestsvc",
  "host": {
    "id": "forestsvc",
    "which": "https://www.fs.usda.gov/",
    "what": "Forest Service [crashed on tabNav]"
  },
  "log": [
    {
      "event": "startTime",
      "value": "2022-07-19T23:08:30"
    },
    {
      "event": "endTime",
      "value": "2022-07-19T23:08:59"
    }
  ],
  "script": {
    "id": "tabNav",
    "what": "tabNav test",
    "strict": true,
    "timeLimit": 30,
    "commands": [
      {
        "type": "launch",
        "which": "chromium",
        "what": "Browser"
      },
      {
        "type": "url",
        "which": "https://www.fs.usda.gov/",
        "what": "Forest Service [crashed on tabNav]"
      },
      {
        "type": "tenonRequest",
        "id": "a",
        "withNewContent": true,
        "what": "Tenon API version 2 test request"
      },
      {
        "type": "test",
        "which": "menuNav",
        "withItems": true,
        "what": "keyboard navigation within true-focus menus"
      },
      {
        "type": "test",
        "which": "tenon",
        "id": "a",
        "what": "Tenon API version 2 result retrieval"
      }
    ]
  },
  "acts": [
    {
      "type": "launch",
      "which": "chromium",
      "what": "Browser"
    },
    {
      "type": "url",
      "which": "https://www.fs.usda.gov/",
      "what": "Forest Service [crashed on tabNav]",
      "result": "https://www.fs.usda.gov/"
    },
    {
      "type": "tenonRequest",
      "id": "a",
      "withNewContent": true,
      "what": "Tenon API version 2 test request",
      "url": "https://www.fs.usda.gov/"
    },
    {
      "type": "test",
      "which": "menuNav",
      "withItems": true,
      "what": "keyboard navigation between focusable menu items",
      "url": "https://www.fs.usda.gov/",
      "result": {
        "totals": {
          "navigations": {
            "all": {
              "total": 0,
              "correct": 0,
              "incorrect": 0
            },
            "specific": {
              "tab": {
                "total": 0,
                "correct": 0,
                "incorrect": 0
              },
              "left": {
                "total": 0,
                "correct": 0,
                "incorrect": 0
              },
              "right": {
                "total": 0,
                "correct": 0,
                "incorrect": 0
              },
              "up": {
                "total": 0,
                "correct": 0,
                "incorrect": 0
              },
              "down": {
                "total": 0,
                "correct": 0,
                "incorrect": 0
              },
              "home": {
                "total": 0,
                "correct": 0,
                "incorrect": 0
              },
              "end": {
                "total": 0,
                "correct": 0,
                "incorrect": 0
              }
            }
          },
          "menuItems": {
            "total": 0,
            "correct": 0,
            "incorrect": 0
          },
          "menus": {
            "total": 0,
            "correct": 0,
            "incorrect": 0
          }
        },
        "menuItems": {
          "incorrect": [],
          "correct": []
        }
      }
    },
    {
      "type": "launch",
      "which": "chromium",
      "what": "chromium browser"
    },
    {
      "type": "url",
      "which": "https://www.fs.usda.gov/",
      "what": "URL",
      "result": "https://www.fs.usda.gov/"
    },
    {
      "type": "test",
      "which": "tenon",
      "id": "a",
      "what": "Tenon",
      "url": "https://www.fs.usda.gov/",
      "result": {
        "status": 200,
        "message": "OK",
        "code": "success",
        "info": "Success",
        "moreInfo": "https://tenon.io/documentation/apiv2/response-codes#success",
        "responseExecTime": "0.065",
        "responseTime": "2022-07-19T23:08:58.939Z",
        "data": {
          "apiErrors": [],
          "documentSize": 1041307,
          "metadata": null,
          "resultSummary": {
            "tests": {
              "total": 180,
              "passing": 171,
              "failing": 9
            },
            "issues": {
              "totalErrors": 35,
              "totalWarnings": 3,
              "totalIssues": 38
            },
            "issuesByLevel": {
              "A": {
                "count": 16,
                "pct": 42.11
              },
              "AA": {
                "count": 12,
                "pct": 31.58
              },
              "AAA": {
                "count": 38,
                "pct": 100
              }
            },
            "density": {
              "errorDensity": 3,
              "warningDensity": 0,
              "allDensity": 4
            }
          },
          "projectID": "04CDF65C-DEE7-6E37-78E8-5A9472A3",
          "responseID": "5ed616d5-07a8-49ee-b1de-b23edb99c5c7",
          "docID": "dcf66388-e66c-4491-eb3a-44343be42699",
          "sourceHash": "bcf23d698018d859b8c017b41b0d8bf0",
          "urlHttpCode": 200,
          "clientScriptErrors": [],
          "remainingApiCalls": {
            "planCalls": 0,
            "boosts": 20
          },
          "globalStats": {
            "errorDensity": "N/A",
            "warningDensity": "N/A",
            "allDensity": "N/A",
            "stdDev": "N/A"
          },
          "resultUrl": "http://ngnix/history.php?responseID=5ed616d5-07a8-49ee-b1de-b23edb99c5c7",
          "resultSet": [
            {
              "tID": 28,
              "bpID": 3,
              "priority": 100,
              "level": [
                "AAA"
              ],
              "certainty": 100,
              "errorTitle": "The layout or sizing of this page causes horizontal scrolling.",
              "standards": [
                "Web Content Accessibility Guidelines (WCAG) 2.0, Level AAA: 1.4.8 Visual Presentation"
              ],
              "resultTitle": "Avoid layouts that result in horizontal scroll",
              "errorDescription": "This page is too wide, causing horizontal scrolling (at the tested viewport size). Horizontal scrolling will cause difficulties for users with low vision, especially if they have their monitor set to a low resolution. Review HTML, CSS and page element sizes to ensure 100% width is not exceeded.",
              "viewPortLocation": {
                "top-left": {
                  "x": 0,
                  "y": 0
                },
                "bottom-right": {
                  "x": 1024,
                  "y": 2829.08
                },
                "height": 2829.08,
                "width": 1024
              },
              "position": {
                "line": 2169,
                "column": 60
              },
              "errorSnippet": "&lt;body data-once=\"b-root\"&gt;\n&lt;a href=\"#main-content\" class=\"usa-sr-only focusable\" data-kmt=\"1\"&gt; Skip to main content\n&lt;/a&gt; &lt;div class=\"dialog-off-canvas-main-canvas\" data-off-canvas-main-canvas=\"\"&gt; &lt;section class=\"usa-banner\"&gt; ",
              "xpath": "/html/body",
              "issueID": "3a40ada67154b5757a54f6f86f2addbf",
              "signature": "2bce1f1c2be5def2e5fe3c7ba7ed38f0",
              "ref": "https://tenon.io/bestpractice.php?bpID=3&tID=28&issueID=3a40ada67154b5757a54f6f86f2addbf"
            },
            {
              "tID": 98,
              "bpID": 105,
              "priority": 100,
              "level": [
                "A",
                "AAA"
              ],
              "certainty": 100,
              "errorTitle": "These links have the same text but different destinations.",
              "standards": [
                "Web Content Accessibility Guidelines (WCAG) 2.0, Level A: 2.4.4 Link Purpose (In Context)",
                "Web Content Accessibility Guidelines (WCAG) 2.0, Level AAA: 2.4.9 Link Purpose (Link Only)"
              ],
              "resultTitle": "Don't reuse the same link text for links that have different destinations",
              "errorDescription": "This link has the same text as another link that goes to a different place. Using the same text for multiple links which point to different pages is ambiguous and may be confusing for assistive technology users, or for users who have a cognitive disability. Link text should tell the user where they will go if they follow the link. If two links on a page go to two different destinations, use different link text that accurately and concisely describes their destination.",
              "viewPortLocation": {
                "top-left": {
                  "x": 0,
                  "y": 0
                },
                "bottom-right": {
                  "x": 0,
                  "y": 0
                },
                "height": 0,
                "width": 0
              },
              "position": {
                "line": 134,
                "column": 0
              },
              "errorSnippet": "&lt;a href=\"/managing-land/national-forests-grasslands\" class=\"link\" data-drupal-link-system-path=\"node/213400\" data-kmt=\"1\"&gt;Forests and Grasslands&lt;/a&gt;",
              "xpath": "/html/body/div[1]/header[1]/nav[1]/div[1]/ul[1]/li[2]/ul[1]/li[2]/a[1]",
              "issueID": "7a29ea1fdbf69c6f0fc63da47803254c",
              "signature": "37670fd269545726af63dbb2eec47f6f",
              "ref": "https://tenon.io/bestpractice.php?bpID=105&tID=98&issueID=7a29ea1fdbf69c6f0fc63da47803254c"
            },
            {
              "tID": 98,
              "bpID": 105,
              "priority": 100,
              "level": [
                "A",
                "AAA"
              ],
              "certainty": 100,
              "errorTitle": "These links have the same text but different destinations.",
              "standards": [
                "Web Content Accessibility Guidelines (WCAG) 2.0, Level A: 2.4.4 Link Purpose (In Context)",
                "Web Content Accessibility Guidelines (WCAG) 2.0, Level AAA: 2.4.9 Link Purpose (Link Only)"
              ],
              "resultTitle": "Don't reuse the same link text for links that have different destinations",
              "errorDescription": "This link has the same text as another link that goes to a different place. Using the same text for multiple links which point to different pages is ambiguous and may be confusing for assistive technology users, or for users who have a cognitive disability. Link text should tell the user where they will go if they follow the link. If two links on a page go to two different destinations, use different link text that accurately and concisely describes their destination.",
              "viewPortLocation": {
                "top-left": {
                  "x": 144,
                  "y": 857.25
                },
                "bottom-right": {
                  "x": 319,
                  "y": 871.25
                },
                "height": 14,
                "width": 175
              },
              "position": {
                "line": 6532,
                "column": 0
              },
              "errorSnippet": "&lt;a href=\"https://www.fs.usda.gov/faces-of-the-forest-service\" data-kmt=\"1\"&gt;Faces of the Forest Service&lt;/a&gt;",
              "xpath": "/html/body/div[1]/main[1]/div[3]/article[1]/div[1]/div[2]/div[1]/div[1]/div[1]/div[1]/div[1]/a[2]",
              "issueID": "39eaa58bea85b39bf0d9f203ae49643d",
              "signature": "a253ff6dd0e00411d2ec0d22dbf29e7b",
              "ref": "https://tenon.io/bestpractice.php?bpID=105&tID=98&issueID=39eaa58bea85b39bf0d9f203ae49643d"
            },
            {
              "tID": 129,
              "bpID": 211,
              "priority": 85,
              "level": [
                "A",
                "AA",
                "AAA"
              ],
              "certainty": 100,
              "errorTitle": "CSS underline on text has been detected that is not a link.",
              "standards": [
                "Web Content Accessibility Guidelines (WCAG) 2.0, Level A: 1.3.1 Info and Relationships",
                "Web Content Accessibility Guidelines (WCAG) 2.0, Level AA: 1.4.5 Images of Text",
                "Web Content Accessibility Guidelines (WCAG) 2.0, Level AA: 3.2.4 Consistent Identification",
                "Web Content Accessibility Guidelines (WCAG) 2.0, Level AA: 1.4.4 Resize text",
                "Web Content Accessibility Guidelines (WCAG) 2.0, Level AAA: 2.5.5 Target Size"
              ],
              "resultTitle": "Ensure content is legible.",
              "errorDescription": "The text in this passage has been styled to display underlined but it is not a link. Underlined text on the web or on apps is universally accepted as signifying that the relevant text is a link. Applying underline to text that is not a link is likely to confuse many users, and especially people with cognitive impairments, learning disabilities or dyslexia. Remove the underlining from this passage of text.",
              "viewPortLocation": {
                "top-left": {
                  "x": 0,
                  "y": -2
                },
                "bottom-right": {
                  "x": 133,
                  "y": 14
                },
                "height": 16,
                "width": 133
              },
              "position": {
                "line": 2964,
                "column": 138
              },
              "errorSnippet": "&lt;p class=\"usa-banner__header-action\" aria-hidden=\"true\" style=\"\"&gt;Here’s how you know&lt;/p&gt;",
              "xpath": "/html/body/div[1]/section[1]/div[1]/div[1]/header[1]/div[1]/div[2]/p[2]",
              "issueID": "b84d0b620a5f1c0359f5ac426ba00ac0",
              "signature": "957d37438d2832a9932f93bcd8582154",
              "ref": "https://tenon.io/bestpractice.php?bpID=211&tID=129&issueID=b84d0b620a5f1c0359f5ac426ba00ac0"
            },
            {
              "tID": 129,
              "bpID": 211,
              "priority": 85,
              "level": [
                "A",
                "AA",
                "AAA"
              ],
              "certainty": 100,
              "errorTitle": "CSS underline on text has been detected that is not a link.",
              "standards": [
                "Web Content Accessibility Guidelines (WCAG) 2.0, Level A: 1.3.1 Info and Relationships",
                "Web Content Accessibility Guidelines (WCAG) 2.0, Level AA: 1.4.5 Images of Text",
                "Web Content Accessibility Guidelines (WCAG) 2.0, Level AA: 3.2.4 Consistent Identification",
                "Web Content Accessibility Guidelines (WCAG) 2.0, Level AA: 1.4.4 Resize text",
                "Web Content Accessibility Guidelines (WCAG) 2.0, Level AAA: 2.5.5 Target Size"
              ],
              "resultTitle": "Ensure content is legible.",
              "errorDescription": "The text in this passage has been styled to display underlined but it is not a link. Underlined text on the web or on apps is universally accepted as signifying that the relevant text is a link. Applying underline to text that is not a link is likely to confuse many users, and especially people with cognitive impairments, learning disabilities or dyslexia. Remove the underlining from this passage of text.",
              "viewPortLocation": {
                "top-left": {
                  "x": 0,
                  "y": 0
                },
                "bottom-right": {
                  "x": 117,
                  "y": 14
                },
                "height": 14,
                "width": 117
              },
              "position": {
                "line": 7859,
                "column": 11
              },
              "errorSnippet": "&lt;span class=\"usa-banner__button-text\"&gt;Here's how you know&lt;/span&gt;",
              "xpath": "/html/body/div[1]/section[1]/div[1]/div[1]/header[1]/div[1]/button[1]/span[1]",
              "issueID": "fd95cb8b4829c6ddf3f1ee82ef949b23",
              "signature": "cdbff4d5b5b0efa6a4574e60f847e91f",
              "ref": "https://tenon.io/bestpractice.php?bpID=211&tID=129&issueID=fd95cb8b4829c6ddf3f1ee82ef949b23"
            },
            {
              "tID": 144,
              "bpID": 14,
              "priority": 91,
              "level": [
                "AAA"
              ],
              "certainty": 100,
              "errorTitle": "This content's line height is insufficent to properly display the computed element font size.",
              "standards": [
                "Web Content Accessibility Guidelines (WCAG) 2.0, Level AAA: 1.4.8 Visual Presentation"
              ],
              "resultTitle": "Set a `line-height` (leading) that is at least one and a half times the current font size.",
              "errorDescription": "This content's line height is insufficent to properly display the computed element font size. Line height that is less than 150% of the computed element font size limits content readability for people with dyslexia, low vision, cognitive impairments or learning disabilities. Set the `line-height` for this content to a value of 1.5 or higher. Using a proportional, unitless value like 1.5 or 150% will ensure that the line-height scales if the user zooms the browser window.",
              "viewPortLocation": {
                "top-left": {
                  "x": 0,
                  "y": 0
                },
                "bottom-right": {
                  "x": 1024,
                  "y": 2829.08
                },
                "height": 2829.08,
                "width": 1024
              },
              "position": {
                "line": 2169,
                "column": 60
              },
              "errorSnippet": "&lt;body data-once=\"b-root\"&gt;\n&lt;a href=\"#main-content\" class=\"usa-sr-only focusable\" data-kmt=\"1\"&gt; Skip to main content\n&lt;/a&gt; &lt;div class=\"dialog-off-canvas-main-canvas\" data-off-canvas-main-canvas=\"\"&gt; &lt;section class=\"usa-banner\"&gt; ",
              "xpath": "/html/body",
              "issueID": "82750b210b61287f1d4b1829b6da3249",
              "signature": "951c61cd43740785ce8fb6c5f110a315",
              "ref": "https://tenon.io/bestpractice.php?bpID=14&tID=144&issueID=82750b210b61287f1d4b1829b6da3249"
            },
            {
              "tID": 144,
              "bpID": 14,
              "priority": 91,
              "level": [
                "AAA"
              ],
              "certainty": 100,
              "errorTitle": "This content's line height is insufficent to properly display the computed element font size.",
              "standards": [
                "Web Content Accessibility Guidelines (WCAG) 2.0, Level AAA: 1.4.8 Visual Presentation"
              ],
              "resultTitle": "Set a `line-height` (leading) that is at least one and a half times the current font size.",
              "errorDescription": "This content's line height is insufficent to properly display the computed element font size. Line height that is less than 150% of the computed element font size limits content readability for people with dyslexia, low vision, cognitive impairments or learning disabilities. Set the `line-height` for this content to a value of 1.5 or higher. Using a proportional, unitless value like 1.5 or 150% will ensure that the line-height scales if the user zooms the browser window.",
              "viewPortLocation": {
                "top-left": {
                  "x": 0,
                  "y": 80
                },
                "bottom-right": {
                  "x": 1024,
                  "y": 142
                },
                "height": 62,
                "width": 1024
              },
              "position": {
                "line": 7938,
                "column": 3
              },
              "errorSnippet": "&lt;nav class=\"usa-nav bg-primary-dark text-white\" role=\"navigation\"&gt; &lt;div class=\"usa-nav__inner\"&gt; &lt;button class=\"usa-nav__close\" style=\"\"&gt; &lt;img src=\"/themes/custom/fs_uswds/assets/img/close-white.svg\" alt=\"close\"&gt; &lt;/button&gt; &l",
              "xpath": "/html/body/div[1]/header[1]/nav[1]",
              "issueID": "fa1f2f6ac24b5a83e876b4b7eca89377",
              "signature": "3af6619b99ef63c64a20021a2bf5c832",
              "ref": "https://tenon.io/bestpractice.php?bpID=14&tID=144&issueID=fa1f2f6ac24b5a83e876b4b7eca89377"
            },
            {
              "tID": 144,
              "bpID": 14,
              "priority": 91,
              "level": [
                "AAA"
              ],
              "certainty": 100,
              "errorTitle": "This content's line height is insufficent to properly display the computed element font size.",
              "standards": [
                "Web Content Accessibility Guidelines (WCAG) 2.0, Level AAA: 1.4.8 Visual Presentation"
              ],
              "resultTitle": "Set a `line-height` (leading) that is at least one and a half times the current font size.",
              "errorDescription": "This content's line height is insufficent to properly display the computed element font size. Line height that is less than 150% of the computed element font size limits content readability for people with dyslexia, low vision, cognitive impairments or learning disabilities. Set the `line-height` for this content to a value of 1.5 or higher. Using a proportional, unitless value like 1.5 or 150% will ensure that the line-height scales if the user zooms the browser window.",
              "viewPortLocation": {
                "top-left": {
                  "x": 0,
                  "y": 8
                },
                "bottom-right": {
                  "x": 84,
                  "y": 54
                },
                "height": 46,
                "width": 84
              },
              "position": {
                "line": 50,
                "column": 3
              },
              "errorSnippet": "&lt;li class=\"usa-nav__primary-item\"&gt; &lt;button class=\"usa-accordion__button usa-nav__link \" aria-expanded=\"false\" aria-controls=\"basic-nav-section-1\"&gt; &lt;span&gt;Visit Us&lt;/span&gt; &lt;/button&gt; &lt;ul id=\"basic-nav-section-1\" class=\"usa-na",
              "xpath": "/html/body/div[1]/header[1]/nav[1]/div[1]/ul[1]/li[1]",
              "issueID": "2f7bd65a6e4e250469a6cd9c9b7d1570",
              "signature": "f588821bdcb116dca8d0b68a115d0c7f",
              "ref": "https://tenon.io/bestpractice.php?bpID=14&tID=144&issueID=2f7bd65a6e4e250469a6cd9c9b7d1570"
            },
            {
              "tID": 144,
              "bpID": 14,
              "priority": 91,
              "level": [
                "AAA"
              ],
              "certainty": 100,
              "errorTitle": "This content's line height is insufficent to properly display the computed element font size.",
              "standards": [
                "Web Content Accessibility Guidelines (WCAG) 2.0, Level AAA: 1.4.8 Visual Presentation"
              ],
              "resultTitle": "Set a `line-height` (leading) that is at least one and a half times the current font size.",
              "errorDescription": "This content's line height is insufficent to properly display the computed element font size. Line height that is less than 150% of the computed element font size limits content readability for people with dyslexia, low vision, cognitive impairments or learning disabilities. Set the `line-height` for this content to a value of 1.5 or higher. Using a proportional, unitless value like 1.5 or 150% will ensure that the line-height scales if the user zooms the browser window.",
              "viewPortLocation": {
                "top-left": {
                  "x": 84,
                  "y": 8
                },
                "bottom-right": {
                  "x": 245,
                  "y": 54
                },
                "height": 46,
                "width": 161
              },
              "position": {
                "line": 82,
                "column": 3
              },
              "errorSnippet": "&lt;li class=\"usa-nav__primary-item\"&gt; &lt;button class=\"usa-accordion__button usa-nav__link \" aria-expanded=\"false\" aria-controls=\"basic-nav-section-2\"&gt; &lt;span&gt;Managing the Land&lt;/span&gt; &lt;/button&gt; &lt;ul id=\"basic-nav-section-2\" clas",
              "xpath": "/html/body/div[1]/header[1]/nav[1]/div[1]/ul[1]/li[2]",
              "issueID": "7c1c52e6f57078593c869c2eb9238a9d",
              "signature": "a2201e6bafa07b25382a51b1bb905f5b",
              "ref": "https://tenon.io/bestpractice.php?bpID=14&tID=144&issueID=7c1c52e6f57078593c869c2eb9238a9d"
            },
            {
              "tID": 144,
              "bpID": 14,
              "priority": 91,
              "level": [
                "AAA"
              ],
              "certainty": 100,
              "errorTitle": "This content's line height is insufficent to properly display the computed element font size.",
              "standards": [
                "Web Content Accessibility Guidelines (WCAG) 2.0, Level AAA: 1.4.8 Visual Presentation"
              ],
              "resultTitle": "Set a `line-height` (leading) that is at least one and a half times the current font size.",
              "errorDescription": "This content's line height is insufficent to properly display the computed element font size. Line height that is less than 150% of the computed element font size limits content readability for people with dyslexia, low vision, cognitive impairments or learning disabilities. Set the `line-height` for this content to a value of 1.5 or higher. Using a proportional, unitless value like 1.5 or 150% will ensure that the line-height scales if the user zooms the browser window.",
              "viewPortLocation": {
                "top-left": {
                  "x": 245,
                  "y": 8
                },
                "bottom-right": {
                  "x": 316,
                  "y": 54
                },
                "height": 46,
                "width": 71
              },
              "position": {
                "line": 93,
                "column": 3
              },
              "errorSnippet": "&lt;li class=\"usa-nav__primary-item\"&gt; &lt;button class=\"usa-accordion__button usa-nav__link \" aria-expanded=\"false\" aria-controls=\"basic-nav-section-3\"&gt; &lt;span&gt;Learn&lt;/span&gt; &lt;/button&gt; &lt;ul id=\"basic-nav-section-3\" class=\"usa-nav__",
              "xpath": "/html/body/div[1]/header[1]/nav[1]/div[1]/ul[1]/li[3]",
              "issueID": "4721e57f710685048fc61f8908c47ce8",
              "signature": "fca8306e8939c1d1e8a030b1a4c74c6b",
              "ref": "https://tenon.io/bestpractice.php?bpID=14&tID=144&issueID=4721e57f710685048fc61f8908c47ce8"
            },
            {
              "tID": 144,
              "bpID": 14,
              "priority": 91,
              "level": [
                "AAA"
              ],
              "certainty": 100,
              "errorTitle": "This content's line height is insufficent to properly display the computed element font size.",
              "standards": [
                "Web Content Accessibility Guidelines (WCAG) 2.0, Level AAA: 1.4.8 Visual Presentation"
              ],
              "resultTitle": "Set a `line-height` (leading) that is at least one and a half times the current font size.",
              "errorDescription": "This content's line height is insufficent to properly display the computed element font size. Line height that is less than 150% of the computed element font size limits content readability for people with dyslexia, low vision, cognitive impairments or learning disabilities. Set the `line-height` for this content to a value of 1.5 or higher. Using a proportional, unitless value like 1.5 or 150% will ensure that the line-height scales if the user zooms the browser window.",
              "viewPortLocation": {
                "top-left": {
                  "x": 316,
                  "y": 8
                },
                "bottom-right": {
                  "x": 512,
                  "y": 54
                },
                "height": 46,
                "width": 196
              },
              "position": {
                "line": 100,
                "column": 3
              },
              "errorSnippet": "&lt;li class=\"usa-nav__primary-item\"&gt; &lt;button class=\"usa-accordion__button usa-nav__link \" aria-expanded=\"false\" aria-controls=\"basic-nav-section-4\"&gt; &lt;span&gt;Science and Technology&lt;/span&gt; &lt;/button&gt; &lt;ul id=\"basic-nav-section-4\"",
              "xpath": "/html/body/div[1]/header[1]/nav[1]/div[1]/ul[1]/li[4]",
              "issueID": "9ec89d03fafa36f182d9e4507c388e8f",
              "signature": "2c722588b766a82dcc4b4995f7e6bbed",
              "ref": "https://tenon.io/bestpractice.php?bpID=14&tID=144&issueID=9ec89d03fafa36f182d9e4507c388e8f"
            },
            {
              "tID": 144,
              "bpID": 14,
              "priority": 91,
              "level": [
                "AAA"
              ],
              "certainty": 100,
              "errorTitle": "This content's line height is insufficent to properly display the computed element font size.",
              "standards": [
                "Web Content Accessibility Guidelines (WCAG) 2.0, Level AAA: 1.4.8 Visual Presentation"
              ],
              "resultTitle": "Set a `line-height` (leading) that is at least one and a half times the current font size.",
              "errorDescription": "This content's line height is insufficent to properly display the computed element font size. Line height that is less than 150% of the computed element font size limits content readability for people with dyslexia, low vision, cognitive impairments or learning disabilities. Set the `line-height` for this content to a value of 1.5 or higher. Using a proportional, unitless value like 1.5 or 150% will ensure that the line-height scales if the user zooms the browser window.",
              "viewPortLocation": {
                "top-left": {
                  "x": 512,
                  "y": 8
                },
                "bottom-right": {
                  "x": 653,
                  "y": 54
                },
                "height": 46,
                "width": 141
              },
              "position": {
                "line": 110,
                "column": 3
              },
              "errorSnippet": "&lt;li class=\"usa-nav__primary-item\"&gt; &lt;button class=\"usa-accordion__button usa-nav__link \" aria-expanded=\"false\" aria-controls=\"basic-nav-section-5\"&gt; &lt;span&gt;Working with Us&lt;/span&gt; &lt;/button&gt; &lt;ul id=\"basic-nav-section-5\" class=",
              "xpath": "/html/body/div[1]/header[1]/nav[1]/div[1]/ul[1]/li[5]",
              "issueID": "0ec41aa46eed71c59cb1c85b4a113480",
              "signature": "bdc1e42061a6b6de9fd7eac303afe2ca",
              "ref": "https://tenon.io/bestpractice.php?bpID=14&tID=144&issueID=0ec41aa46eed71c59cb1c85b4a113480"
            },
            {
              "tID": 144,
              "bpID": 14,
              "priority": 91,
              "level": [
                "AAA"
              ],
              "certainty": 100,
              "errorTitle": "This content's line height is insufficent to properly display the computed element font size.",
              "standards": [
                "Web Content Accessibility Guidelines (WCAG) 2.0, Level AAA: 1.4.8 Visual Presentation"
              ],
              "resultTitle": "Set a `line-height` (leading) that is at least one and a half times the current font size.",
              "errorDescription": "This content's line height is insufficent to properly display the computed element font size. Line height that is less than 150% of the computed element font size limits content readability for people with dyslexia, low vision, cognitive impairments or learning disabilities. Set the `line-height` for this content to a value of 1.5 or higher. Using a proportional, unitless value like 1.5 or 150% will ensure that the line-height scales if the user zooms the browser window.",
              "viewPortLocation": {
                "top-left": {
                  "x": 653,
                  "y": 8
                },
                "bottom-right": {
                  "x": 806,
                  "y": 54
                },
                "height": 46,
                "width": 153
              },
              "position": {
                "line": 7998,
                "column": 15
              },
              "errorSnippet": "&lt;li class=\"usa-nav__primary-item\"&gt; &lt;button class=\"usa-accordion__button usa-nav__link \" aria-expanded=\"false\" aria-controls=\"basic-nav-section-6\"&gt; &lt;span&gt;About the Agency&lt;/span&gt; &lt;/button&gt; &lt;ul id=\"basic-nav-section-6\" class",
              "xpath": "/html/body/div[1]/header[1]/nav[1]/div[1]/ul[1]/li[6]",
              "issueID": "2c13a47d93d3f0352f55ba13457e9f59",
              "signature": "4beca0c8fae05dcb66b1d0bafe94bf9f",
              "ref": "https://tenon.io/bestpractice.php?bpID=14&tID=144&issueID=2c13a47d93d3f0352f55ba13457e9f59"
            },
            {
              "tID": 144,
              "bpID": 14,
              "priority": 91,
              "level": [
                "AAA"
              ],
              "certainty": 100,
              "errorTitle": "This content's line height is insufficent to properly display the computed element font size.",
              "standards": [
                "Web Content Accessibility Guidelines (WCAG) 2.0, Level AAA: 1.4.8 Visual Presentation"
              ],
              "resultTitle": "Set a `line-height` (leading) that is at least one and a half times the current font size.",
              "errorDescription": "This content's line height is insufficent to properly display the computed element font size. Line height that is less than 150% of the computed element font size limits content readability for people with dyslexia, low vision, cognitive impairments or learning disabilities. Set the `line-height` for this content to a value of 1.5 or higher. Using a proportional, unitless value like 1.5 or 150% will ensure that the line-height scales if the user zooms the browser window.",
              "viewPortLocation": {
                "top-left": {
                  "x": 806,
                  "y": 8
                },
                "bottom-right": {
                  "x": 925,
                  "y": 54
                },
                "height": 46,
                "width": 119
              },
              "position": {
                "line": 8143,
                "column": 15
              },
              "errorSnippet": "&lt;li class=\"usa-nav__primary-item\"&gt; &lt;button class=\"usa-accordion__button usa-nav__link \" aria-expanded=\"false\" aria-controls=\"basic-nav-section-7\"&gt; &lt;span&gt;Inside the FS&lt;/span&gt; &lt;/button&gt; &lt;ul id=\"basic-nav-section-7\" class=\"u",
              "xpath": "/html/body/div[1]/header[1]/nav[1]/div[1]/ul[1]/li[7]",
              "issueID": "616dc9d296da191733c3641f1774bfc9",
              "signature": "6d5a6da7fc818a7813c7b3ea89f068a4",
              "ref": "https://tenon.io/bestpractice.php?bpID=14&tID=144&issueID=616dc9d296da191733c3641f1774bfc9"
            },
            {
              "tID": 144,
              "bpID": 14,
              "priority": 91,
              "level": [
                "AAA"
              ],
              "certainty": 100,
              "errorTitle": "This content's line height is insufficent to properly display the computed element font size.",
              "standards": [
                "Web Content Accessibility Guidelines (WCAG) 2.0, Level AAA: 1.4.8 Visual Presentation"
              ],
              "resultTitle": "Set a `line-height` (leading) that is at least one and a half times the current font size.",
              "errorDescription": "This content's line height is insufficent to properly display the computed element font size. Line height that is less than 150% of the computed element font size limits content readability for people with dyslexia, low vision, cognitive impairments or learning disabilities. Set the `line-height` for this content to a value of 1.5 or higher. Using a proportional, unitless value like 1.5 or 150% will ensure that the line-height scales if the user zooms the browser window.",
              "viewPortLocation": {
                "top-left": {
                  "x": 32,
                  "y": 181.828125
                },
                "bottom-right": {
                  "x": 528,
                  "y": 219.828125
                },
                "height": 38,
                "width": 496
              },
              "position": {
                "line": 8936,
                "column": 0
              },
              "errorSnippet": "&lt;div class=\"font-sans-md\"&gt; &lt;p&gt;Join the National Forest Foundation July 11-17 to celebrate our National Forests. Visit nationalforestweek.org to learn more.&lt;/p&gt; &lt;/div&gt;",
              "xpath": "/html/body/div[1]/main[1]/div[3]/article[1]/div[1]/div[1]/div[1]/div[1]/div[1]/div[1]/div[1]/div[1]/div[1]/div[1]/div[1]/div[1]/div[1]/div[1]/a[1]/div[2]/div[1]/div[1]",
              "issueID": "3e14b55cfef5430c12b81c0787dd8d64",
              "signature": "78712f7ae5659ccbd71e0081a33b6808",
              "ref": "https://tenon.io/bestpractice.php?bpID=14&tID=144&issueID=3e14b55cfef5430c12b81c0787dd8d64"
            },
            {
              "tID": 144,
              "bpID": 14,
              "priority": 91,
              "level": [
                "AAA"
              ],
              "certainty": 100,
              "errorTitle": "This content's line height is insufficent to properly display the computed element font size.",
              "standards": [
                "Web Content Accessibility Guidelines (WCAG) 2.0, Level AAA: 1.4.8 Visual Presentation"
              ],
              "resultTitle": "Set a `line-height` (leading) that is at least one and a half times the current font size.",
              "errorDescription": "This content's line height is insufficent to properly display the computed element font size. Line height that is less than 150% of the computed element font size limits content readability for people with dyslexia, low vision, cognitive impairments or learning disabilities. Set the `line-height` for this content to a value of 1.5 or higher. Using a proportional, unitless value like 1.5 or 150% will ensure that the line-height scales if the user zooms the browser window.",
              "viewPortLocation": {
                "top-left": {
                  "x": 32,
                  "y": 181.828125
                },
                "bottom-right": {
                  "x": 528,
                  "y": 238.828125
                },
                "height": 57,
                "width": 496
              },
              "position": {
                "line": 8992,
                "column": 0
              },
              "errorSnippet": "&lt;div class=\"font-sans-md\"&gt; &lt;p&gt;Taking action to increase firefighter pay, create a new occupational series, and stand-up mental health and well-being programs.&lt;/p&gt; &lt;/div&gt;",
              "xpath": "/html/body/div[1]/main[1]/div[3]/article[1]/div[1]/div[1]/div[1]/div[1]/div[1]/div[1]/div[1]/div[1]/div[1]/div[1]/div[3]/div[1]/div[1]/div[1]/a[1]/div[2]/div[1]/div[1]",
              "issueID": "a6c722902a43ecad7caed5d21e380cf8",
              "signature": "63aa14be2a27783e4409c69b094563bc",
              "ref": "https://tenon.io/bestpractice.php?bpID=14&tID=144&issueID=a6c722902a43ecad7caed5d21e380cf8"
            },
            {
              "tID": 144,
              "bpID": 14,
              "priority": 91,
              "level": [
                "AAA"
              ],
              "certainty": 100,
              "errorTitle": "This content's line height is insufficent to properly display the computed element font size.",
              "standards": [
                "Web Content Accessibility Guidelines (WCAG) 2.0, Level AAA: 1.4.8 Visual Presentation"
              ],
              "resultTitle": "Set a `line-height` (leading) that is at least one and a half times the current font size.",
              "errorDescription": "This content's line height is insufficent to properly display the computed element font size. Line height that is less than 150% of the computed element font size limits content readability for people with dyslexia, low vision, cognitive impairments or learning disabilities. Set the `line-height` for this content to a value of 1.5 or higher. Using a proportional, unitless value like 1.5 or 150% will ensure that the line-height scales if the user zooms the browser window.",
              "viewPortLocation": {
                "top-left": {
                  "x": 32,
                  "y": 118.15625
                },
                "bottom-right": {
                  "x": 661.328,
                  "y": 252.15625
                },
                "height": 134,
                "width": 629.328
              },
              "position": {
                "line": 134,
                "column": 0
              },
              "errorSnippet": "&lt;form action=\"/\" method=\"post\" id=\"fs-search-find-a-forest-form\" accept-charset=\"UTF-8\" class=\"usa-form\" data-kmt=\"1\"&gt; &lt;input autocomplete=\"off\" data-drupal-selector=\"form-ai8vu43ecsrnli7rfoyrjs-p5ujllkugenatrczs73c\" type=\"hidden\" name=\"form_bui",
              "xpath": "/html/body/div[1]/main[1]/div[3]/article[1]/div[1]/div[1]/div[2]/div[1]/div[1]/div[1]/div[1]/form[1]",
              "issueID": "d24732e49a80d0429a47a9e9d1bd1f3d",
              "signature": "73f0196d4b7d9794a8245f643edd7828",
              "ref": "https://tenon.io/bestpractice.php?bpID=14&tID=144&issueID=d24732e49a80d0429a47a9e9d1bd1f3d"
            },
            {
              "tID": 144,
              "bpID": 14,
              "priority": 91,
              "level": [
                "AAA"
              ],
              "certainty": 100,
              "errorTitle": "This content's line height is insufficent to properly display the computed element font size.",
              "standards": [
                "Web Content Accessibility Guidelines (WCAG) 2.0, Level AAA: 1.4.8 Visual Presentation"
              ],
              "resultTitle": "Set a `line-height` (leading) that is at least one and a half times the current font size.",
              "errorDescription": "This content's line height is insufficent to properly display the computed element font size. Line height that is less than 150% of the computed element font size limits content readability for people with dyslexia, low vision, cognitive impairments or learning disabilities. Set the `line-height` for this content to a value of 1.5 or higher. Using a proportional, unitless value like 1.5 or 150% will ensure that the line-height scales if the user zooms the browser window.",
              "viewPortLocation": {
                "top-left": {
                  "x": 12,
                  "y": 18
                },
                "bottom-right": {
                  "x": 316,
                  "y": 156
                },
                "height": 138,
                "width": 304
              },
              "position": {
                "line": 9268,
                "column": 18
              },
              "errorSnippet": "&lt;h3 class=\"featured-title\"&gt;&lt;a href=\"/news/releases/forest-service-and-bureau-land-management-announce-15-day-extension-public-comment\" hreflang=\"en\" data-kmt=\"1\"&gt;Forest Service and Bureau of Land Management Announce 15-day extension of public",
              "xpath": "/html/body/div[1]/main[1]/div[3]/article[1]/div[1]/div[3]/div[1]/div[1]/div[1]/div[2]/div[1]/div[1]/div[1]/div[1]/div[2]/div[2]/h3[1]",
              "issueID": "00ec7ca6d53c06c9b245236c3e1dde2e",
              "signature": "a3267cb25c7ba302fcac86a21ccff009",
              "ref": "https://tenon.io/bestpractice.php?bpID=14&tID=144&issueID=00ec7ca6d53c06c9b245236c3e1dde2e"
            },
            {
              "tID": 144,
              "bpID": 14,
              "priority": 91,
              "level": [
                "AAA"
              ],
              "certainty": 100,
              "errorTitle": "This content's line height is insufficent to properly display the computed element font size.",
              "standards": [
                "Web Content Accessibility Guidelines (WCAG) 2.0, Level AAA: 1.4.8 Visual Presentation"
              ],
              "resultTitle": "Set a `line-height` (leading) that is at least one and a half times the current font size.",
              "errorDescription": "This content's line height is insufficent to properly display the computed element font size. Line height that is less than 150% of the computed element font size limits content readability for people with dyslexia, low vision, cognitive impairments or learning disabilities. Set the `line-height` for this content to a value of 1.5 or higher. Using a proportional, unitless value like 1.5 or 150% will ensure that the line-height scales if the user zooms the browser window.",
              "viewPortLocation": {
                "top-left": {
                  "x": 12,
                  "y": 18
                },
                "bottom-right": {
                  "x": 316,
                  "y": 133
                },
                "height": 115,
                "width": 304
              },
              "position": {
                "line": 9272,
                "column": 18
              },
              "errorSnippet": "&lt;h3 class=\"featured-title\"&gt;&lt;a href=\"/news/releases/usda-forest-service-and-bureau-land-management-seek-public-comments-definitions-other\" hreflang=\"en\" data-kmt=\"1\"&gt;USDA Forest Service and Bureau of Land Management seek public comments on def",
              "xpath": "/html/body/div[1]/main[1]/div[3]/article[1]/div[1]/div[3]/div[1]/div[1]/div[1]/div[2]/div[1]/div[1]/div[1]/div[1]/div[3]/div[2]/h3[1]",
              "issueID": "c2115f8cd0bd2fc9958d64c0ff3137da",
              "signature": "e1aede223f264f787202db853bfde50a",
              "ref": "https://tenon.io/bestpractice.php?bpID=14&tID=144&issueID=c2115f8cd0bd2fc9958d64c0ff3137da"
            },
            {
              "tID": 144,
              "bpID": 14,
              "priority": 91,
              "level": [
                "AAA"
              ],
              "certainty": 100,
              "errorTitle": "This content's line height is insufficent to properly display the computed element font size.",
              "standards": [
                "Web Content Accessibility Guidelines (WCAG) 2.0, Level AAA: 1.4.8 Visual Presentation"
              ],
              "resultTitle": "Set a `line-height` (leading) that is at least one and a half times the current font size.",
              "errorDescription": "This content's line height is insufficent to properly display the computed element font size. Line height that is less than 150% of the computed element font size limits content readability for people with dyslexia, low vision, cognitive impairments or learning disabilities. Set the `line-height` for this content to a value of 1.5 or higher. Using a proportional, unitless value like 1.5 or 150% will ensure that the line-height scales if the user zooms the browser window.",
              "viewPortLocation": {
                "top-left": {
                  "x": 0,
                  "y": 2424.078125
                },
                "bottom-right": {
                  "x": 1024,
                  "y": 2733.078125
                },
                "height": 309,
                "width": 1024
              },
              "position": {
                "line": 9310,
                "column": 0
              },
              "errorSnippet": "&lt;div class=\"usa-footer__primary-content\"&gt; &lt;div class=\"bg-base-lighter\"&gt; &lt;div class=\"grid-container\"&gt; &lt;div class=\"grid-row grid-gap\"&gt; &lt;nav class=\"usa-footer__nav\"&gt; &lt;ul class=\"add-list-reset grid-row grid-gap\"&gt; &lt;li cl",
              "xpath": "/html/body/div[1]/footer[1]/div[2]/div[1]",
              "issueID": "04b3ee6dff428f287f6245c653f9a62b",
              "signature": "fcff091dbda195f4f886c2f6b29e164c",
              "ref": "https://tenon.io/bestpractice.php?bpID=14&tID=144&issueID=04b3ee6dff428f287f6245c653f9a62b"
            },
            {
              "tID": 152,
              "bpID": 211,
              "priority": 88,
              "level": [
                "A",
                "AA",
                "AAA"
              ],
              "certainty": 100,
              "errorTitle": "This actionable element is smaller than the minimum required size.",
              "standards": [
                "Web Content Accessibility Guidelines (WCAG) 2.0, Level A: 1.3.1 Info and Relationships",
                "Web Content Accessibility Guidelines (WCAG) 2.0, Level AA: 1.4.5 Images of Text",
                "Web Content Accessibility Guidelines (WCAG) 2.0, Level AA: 3.2.4 Consistent Identification",
                "Web Content Accessibility Guidelines (WCAG) 2.0, Level AA: 1.4.4 Resize text",
                "Web Content Accessibility Guidelines (WCAG) 2.0, Level AAA: 2.5.5 Target Size"
              ],
              "resultTitle": "Ensure content is legible.",
              "errorDescription": "This actionable element is smaller than the stated minimum defined by all mobile platform developer guides. Minimum sizes for actionable elements ensure that those elements can be operated by people with vision, motor and cognitive disabilities. Even if this system is not explicitly intended for mobile use, it should be enlarged with CSS to meet minimu requirements and improve usability for users with vision, motor and cognitive disabilities.",
              "viewPortLocation": {
                "top-left": {
                  "x": 317,
                  "y": 16
                },
                "bottom-right": {
                  "x": 341,
                  "y": 32
                },
                "height": 16,
                "width": 24
              },
              "position": {
                "line": 3898,
                "column": 34
              },
              "errorSnippet": "&lt;input data-drupal-selector=\"edit-submit-search-api\" type=\"submit\" id=\"edit-submit-search-api\" value=\"GO\" class=\"button js-form-submit form-submit usa-button\"&gt;",
              "xpath": "/html/body/div[1]/header[1]/nav[1]/div[1]/div[1]/div[1]/form[1]/div[2]/input[1]",
              "issueID": "e0c67edffc0e6498bd46507a6c6d8434",
              "signature": "e3a9d06b42ecb8331561711cfcdd5f7c",
              "ref": "https://tenon.io/bestpractice.php?bpID=211&tID=152&issueID=e0c67edffc0e6498bd46507a6c6d8434"
            },
            {
              "tID": 152,
              "bpID": 211,
              "priority": 88,
              "level": [
                "A",
                "AA",
                "AAA"
              ],
              "certainty": 100,
              "errorTitle": "This actionable element is smaller than the minimum required size.",
              "standards": [
                "Web Content Accessibility Guidelines (WCAG) 2.0, Level A: 1.3.1 Info and Relationships",
                "Web Content Accessibility Guidelines (WCAG) 2.0, Level AA: 1.4.5 Images of Text",
                "Web Content Accessibility Guidelines (WCAG) 2.0, Level AA: 3.2.4 Consistent Identification",
                "Web Content Accessibility Guidelines (WCAG) 2.0, Level AA: 1.4.4 Resize text",
                "Web Content Accessibility Guidelines (WCAG) 2.0, Level AAA: 2.5.5 Target Size"
              ],
              "resultTitle": "Ensure content is legible.",
              "errorDescription": "This actionable element is smaller than the stated minimum defined by all mobile platform developer guides. Minimum sizes for actionable elements ensure that those elements can be operated by people with vision, motor and cognitive disabilities. Even if this system is not explicitly intended for mobile use, it should be enlarged with CSS to meet minimu requirements and improve usability for users with vision, motor and cognitive disabilities.",
              "viewPortLocation": {
                "top-left": {
                  "x": 12,
                  "y": 12
                },
                "bottom-right": {
                  "x": 19,
                  "y": 30
                },
                "height": 18,
                "width": 7
              },
              "position": {
                "line": 9076,
                "column": 0
              },
              "errorSnippet": "&lt;button type=\"button\" role=\"tab\" id=\"slick-slide-control00\" aria-controls=\"slick-slide00\" aria-label=\"1 of 5\" tabindex=\"-1\"&gt;1&lt;/button&gt;",
              "xpath": "/html/body/div[1]/main[1]/div[3]/article[1]/div[1]/div[1]/div[1]/div[1]/div[1]/div[1]/div[1]/div[1]/ul[1]/li[1]/button[1]",
              "issueID": "77060329e3e31ab2aa15588531d560d5",
              "signature": "71007b8389a9a6284b02080719283ec4",
              "ref": "https://tenon.io/bestpractice.php?bpID=211&tID=152&issueID=77060329e3e31ab2aa15588531d560d5"
            },
            {
              "tID": 152,
              "bpID": 211,
              "priority": 88,
              "level": [
                "A",
                "AA",
                "AAA"
              ],
              "certainty": 100,
              "errorTitle": "This actionable element is smaller than the minimum required size.",
              "standards": [
                "Web Content Accessibility Guidelines (WCAG) 2.0, Level A: 1.3.1 Info and Relationships",
                "Web Content Accessibility Guidelines (WCAG) 2.0, Level AA: 1.4.5 Images of Text",
                "Web Content Accessibility Guidelines (WCAG) 2.0, Level AA: 3.2.4 Consistent Identification",
                "Web Content Accessibility Guidelines (WCAG) 2.0, Level AA: 1.4.4 Resize text",
                "Web Content Accessibility Guidelines (WCAG) 2.0, Level AAA: 2.5.5 Target Size"
              ],
              "resultTitle": "Ensure content is legible.",
              "errorDescription": "This actionable element is smaller than the stated minimum defined by all mobile platform developer guides. Minimum sizes for actionable elements ensure that those elements can be operated by people with vision, motor and cognitive disabilities. Even if this system is not explicitly intended for mobile use, it should be enlarged with CSS to meet minimu requirements and improve usability for users with vision, motor and cognitive disabilities.",
              "viewPortLocation": {
                "top-left": {
                  "x": 76,
                  "y": 12
                },
                "bottom-right": {
                  "x": 86,
                  "y": 30
                },
                "height": 18,
                "width": 10
              },
              "position": {
                "line": 9076,
                "column": 0
              },
              "errorSnippet": "&lt;button type=\"button\" role=\"tab\" id=\"slick-slide-control01\" aria-controls=\"slick-slide01\" aria-label=\"2 of 5\" tabindex=\"0\" aria-selected=\"true\"&gt;2&lt;/button&gt;",
              "xpath": "/html/body/div[1]/main[1]/div[3]/article[1]/div[1]/div[1]/div[1]/div[1]/div[1]/div[1]/div[1]/div[1]/ul[1]/li[2]/button[1]",
              "issueID": "bb6e105b1bce4b8f90183e1cfd50b40f",
              "signature": "4f425ff9838f4c11c71f17f34d2b1ea6",
              "ref": "https://tenon.io/bestpractice.php?bpID=211&tID=152&issueID=bb6e105b1bce4b8f90183e1cfd50b40f"
            },
            {
              "tID": 152,
              "bpID": 211,
              "priority": 88,
              "level": [
                "A",
                "AA",
                "AAA"
              ],
              "certainty": 100,
              "errorTitle": "This actionable element is smaller than the minimum required size.",
              "standards": [
                "Web Content Accessibility Guidelines (WCAG) 2.0, Level A: 1.3.1 Info and Relationships",
                "Web Content Accessibility Guidelines (WCAG) 2.0, Level AA: 1.4.5 Images of Text",
                "Web Content Accessibility Guidelines (WCAG) 2.0, Level AA: 3.2.4 Consistent Identification",
                "Web Content Accessibility Guidelines (WCAG) 2.0, Level AA: 1.4.4 Resize text",
                "Web Content Accessibility Guidelines (WCAG) 2.0, Level AAA: 2.5.5 Target Size"
              ],
              "resultTitle": "Ensure content is legible.",
              "errorDescription": "This actionable element is smaller than the stated minimum defined by all mobile platform developer guides. Minimum sizes for actionable elements ensure that those elements can be operated by people with vision, motor and cognitive disabilities. Even if this system is not explicitly intended for mobile use, it should be enlarged with CSS to meet minimu requirements and improve usability for users with vision, motor and cognitive disabilities.",
              "viewPortLocation": {
                "top-left": {
                  "x": 140,
                  "y": 12
                },
                "bottom-right": {
                  "x": 150,
                  "y": 30
                },
                "height": 18,
                "width": 10
              },
              "position": {
                "line": 9076,
                "column": 0
              },
              "errorSnippet": "&lt;button type=\"button\" role=\"tab\" id=\"slick-slide-control02\" aria-controls=\"slick-slide02\" aria-label=\"3 of 5\" tabindex=\"-1\"&gt;3&lt;/button&gt;",
              "xpath": "/html/body/div[1]/main[1]/div[3]/article[1]/div[1]/div[1]/div[1]/div[1]/div[1]/div[1]/div[1]/div[1]/ul[1]/li[3]/button[1]",
              "issueID": "91b0cc9647660a87b6dc322f586f4af1",
              "signature": "398a768de27dc3fa8718886c19ad8268",
              "ref": "https://tenon.io/bestpractice.php?bpID=211&tID=152&issueID=91b0cc9647660a87b6dc322f586f4af1"
            },
            {
              "tID": 152,
              "bpID": 211,
              "priority": 88,
              "level": [
                "A",
                "AA",
                "AAA"
              ],
              "certainty": 100,
              "errorTitle": "This actionable element is smaller than the minimum required size.",
              "standards": [
                "Web Content Accessibility Guidelines (WCAG) 2.0, Level A: 1.3.1 Info and Relationships",
                "Web Content Accessibility Guidelines (WCAG) 2.0, Level AA: 1.4.5 Images of Text",
                "Web Content Accessibility Guidelines (WCAG) 2.0, Level AA: 3.2.4 Consistent Identification",
                "Web Content Accessibility Guidelines (WCAG) 2.0, Level AA: 1.4.4 Resize text",
                "Web Content Accessibility Guidelines (WCAG) 2.0, Level AAA: 2.5.5 Target Size"
              ],
              "resultTitle": "Ensure content is legible.",
              "errorDescription": "This actionable element is smaller than the stated minimum defined by all mobile platform developer guides. Minimum sizes for actionable elements ensure that those elements can be operated by people with vision, motor and cognitive disabilities. Even if this system is not explicitly intended for mobile use, it should be enlarged with CSS to meet minimu requirements and improve usability for users with vision, motor and cognitive disabilities.",
              "viewPortLocation": {
                "top-left": {
                  "x": 204,
                  "y": 12
                },
                "bottom-right": {
                  "x": 214,
                  "y": 30
                },
                "height": 18,
                "width": 10
              },
              "position": {
                "line": 9076,
                "column": 0
              },
              "errorSnippet": "&lt;button type=\"button\" role=\"tab\" id=\"slick-slide-control03\" aria-controls=\"slick-slide03\" aria-label=\"4 of 5\" tabindex=\"-1\"&gt;4&lt;/button&gt;",
              "xpath": "/html/body/div[1]/main[1]/div[3]/article[1]/div[1]/div[1]/div[1]/div[1]/div[1]/div[1]/div[1]/div[1]/ul[1]/li[4]/button[1]",
              "issueID": "a2fd27ac26c826aa6404594289933aae",
              "signature": "c61d8e3473342eb7d67bf9ae316cfb8c",
              "ref": "https://tenon.io/bestpractice.php?bpID=211&tID=152&issueID=a2fd27ac26c826aa6404594289933aae"
            },
            {
              "tID": 152,
              "bpID": 211,
              "priority": 88,
              "level": [
                "A",
                "AA",
                "AAA"
              ],
              "certainty": 100,
              "errorTitle": "This actionable element is smaller than the minimum required size.",
              "standards": [
                "Web Content Accessibility Guidelines (WCAG) 2.0, Level A: 1.3.1 Info and Relationships",
                "Web Content Accessibility Guidelines (WCAG) 2.0, Level AA: 1.4.5 Images of Text",
                "Web Content Accessibility Guidelines (WCAG) 2.0, Level AA: 3.2.4 Consistent Identification",
                "Web Content Accessibility Guidelines (WCAG) 2.0, Level AA: 1.4.4 Resize text",
                "Web Content Accessibility Guidelines (WCAG) 2.0, Level AAA: 2.5.5 Target Size"
              ],
              "resultTitle": "Ensure content is legible.",
              "errorDescription": "This actionable element is smaller than the stated minimum defined by all mobile platform developer guides. Minimum sizes for actionable elements ensure that those elements can be operated by people with vision, motor and cognitive disabilities. Even if this system is not explicitly intended for mobile use, it should be enlarged with CSS to meet minimu requirements and improve usability for users with vision, motor and cognitive disabilities.",
              "viewPortLocation": {
                "top-left": {
                  "x": 268,
                  "y": 12
                },
                "bottom-right": {
                  "x": 278,
                  "y": 30
                },
                "height": 18,
                "width": 10
              },
              "position": {
                "line": 9076,
                "column": 0
              },
              "errorSnippet": "&lt;button type=\"button\" role=\"tab\" id=\"slick-slide-control04\" aria-controls=\"slick-slide04\" aria-label=\"5 of 5\" tabindex=\"-1\"&gt;5&lt;/button&gt;",
              "xpath": "/html/body/div[1]/main[1]/div[3]/article[1]/div[1]/div[1]/div[1]/div[1]/div[1]/div[1]/div[1]/div[1]/ul[1]/li[5]/button[1]",
              "issueID": "08fd1185de34576f95e0f70749aca910",
              "signature": "18ceb290171263a8ab2dcc1ee77d20a0",
              "ref": "https://tenon.io/bestpractice.php?bpID=211&tID=152&issueID=08fd1185de34576f95e0f70749aca910"
            },
            {
              "tID": 152,
              "bpID": 211,
              "priority": 88,
              "level": [
                "A",
                "AA",
                "AAA"
              ],
              "certainty": 100,
              "errorTitle": "This actionable element is smaller than the minimum required size.",
              "standards": [
                "Web Content Accessibility Guidelines (WCAG) 2.0, Level A: 1.3.1 Info and Relationships",
                "Web Content Accessibility Guidelines (WCAG) 2.0, Level AA: 1.4.5 Images of Text",
                "Web Content Accessibility Guidelines (WCAG) 2.0, Level AA: 3.2.4 Consistent Identification",
                "Web Content Accessibility Guidelines (WCAG) 2.0, Level AA: 1.4.4 Resize text",
                "Web Content Accessibility Guidelines (WCAG) 2.0, Level AAA: 2.5.5 Target Size"
              ],
              "resultTitle": "Ensure content is legible.",
              "errorDescription": "This actionable element is smaller than the stated minimum defined by all mobile platform developer guides. Minimum sizes for actionable elements ensure that those elements can be operated by people with vision, motor and cognitive disabilities. Even if this system is not explicitly intended for mobile use, it should be enlarged with CSS to meet minimu requirements and improve usability for users with vision, motor and cognitive disabilities.",
              "viewPortLocation": {
                "top-left": {
                  "x": 0,
                  "y": 0
                },
                "bottom-right": {
                  "x": 21,
                  "y": 16
                },
                "height": 16,
                "width": 21
              },
              "position": {
                "line": 6063,
                "column": 34
              },
              "errorSnippet": "&lt;input data-drupal-selector=\"edit-submit\" type=\"submit\" id=\"edit-submit\" name=\"op\" value=\"Go\" class=\"button button--primary js-form-submit form-submit usa-button\"&gt;",
              "xpath": "/html/body/div[1]/main[1]/div[3]/article[1]/div[1]/div[1]/div[2]/div[1]/div[1]/div[1]/div[1]/form[1]/div[1]/div[2]/div[1]/input[1]",
              "issueID": "c389b0ecc315aaad52c8c9e1aa11a97e",
              "signature": "b4eee8650fddd1cb992346f8a46e237e",
              "ref": "https://tenon.io/bestpractice.php?bpID=211&tID=152&issueID=c389b0ecc315aaad52c8c9e1aa11a97e"
            },
            {
              "tID": 152,
              "bpID": 211,
              "priority": 88,
              "level": [
                "A",
                "AA",
                "AAA"
              ],
              "certainty": 100,
              "errorTitle": "This actionable element is smaller than the minimum required size.",
              "standards": [
                "Web Content Accessibility Guidelines (WCAG) 2.0, Level A: 1.3.1 Info and Relationships",
                "Web Content Accessibility Guidelines (WCAG) 2.0, Level AA: 1.4.5 Images of Text",
                "Web Content Accessibility Guidelines (WCAG) 2.0, Level AA: 3.2.4 Consistent Identification",
                "Web Content Accessibility Guidelines (WCAG) 2.0, Level AA: 1.4.4 Resize text",
                "Web Content Accessibility Guidelines (WCAG) 2.0, Level AAA: 2.5.5 Target Size"
              ],
              "resultTitle": "Ensure content is legible.",
              "errorDescription": "This actionable element is smaller than the stated minimum defined by all mobile platform developer guides. Minimum sizes for actionable elements ensure that those elements can be operated by people with vision, motor and cognitive disabilities. Even if this system is not explicitly intended for mobile use, it should be enlarged with CSS to meet minimu requirements and improve usability for users with vision, motor and cognitive disabilities.",
              "viewPortLocation": {
                "top-left": {
                  "x": 0,
                  "y": 233.15625
                },
                "bottom-right": {
                  "x": 331,
                  "y": 252.15625
                },
                "height": 19,
                "width": 331
              },
              "position": {
                "line": 6532,
                "column": 0
              },
              "errorSnippet": "&lt;a href=\"https://www.fs.fed.us/ivm/\" data-kmt=\"1\"&gt;&lt;img loading=\"lazy\" src=\"/sites/default/files/styles/original/public/2021-02/ivm.jpg?itok=ktYd-rIV\" width=\"600\" height=\"382\" alt=\"IVM\" typeof=\"Image\"&gt;&lt;/a&gt;",
              "xpath": "/html/body/div[1]/main[1]/div[3]/article[1]/div[1]/div[1]/div[2]/div[1]/div[1]/div[2]/div[1]/div[1]/strong[1]/div[1]/div[1]/strong[1]/a[1]",
              "issueID": "d36446a9a58ef1e2cf1a316f97de9bcc",
              "signature": "b489bb03b44438187f65182848709f54",
              "ref": "https://tenon.io/bestpractice.php?bpID=211&tID=152&issueID=d36446a9a58ef1e2cf1a316f97de9bcc"
            },
            {
              "tID": 153,
              "bpID": 211,
              "priority": 85,
              "level": [
                "A",
                "AA",
                "AAA"
              ],
              "certainty": 60,
              "errorTitle": "This long string of text is in all caps.",
              "standards": [
                "Web Content Accessibility Guidelines (WCAG) 2.0, Level A: 1.3.1 Info and Relationships",
                "Web Content Accessibility Guidelines (WCAG) 2.0, Level AA: 1.4.5 Images of Text",
                "Web Content Accessibility Guidelines (WCAG) 2.0, Level AA: 3.2.4 Consistent Identification",
                "Web Content Accessibility Guidelines (WCAG) 2.0, Level AA: 1.4.4 Resize text",
                "Web Content Accessibility Guidelines (WCAG) 2.0, Level AAA: 2.5.5 Target Size"
              ],
              "resultTitle": "Ensure content is legible.",
              "errorDescription": "This element contains a long passage of text that is capitalized, either in the text itself or via CSS text-transform.  Capitalized text can be very difficult to read for users with dyslexia Modify this passage of text so that it is no longer all in upper case. Changing this to sentence case will result in significant improvements in readability.",
              "viewPortLocation": {
                "top-left": {
                  "x": 161.515625,
                  "y": 37
                },
                "bottom-right": {
                  "x": 458.515625,
                  "y": 57
                },
                "height": 20,
                "width": 297
              },
              "position": {
                "line": 7926,
                "column": 7
              },
              "errorSnippet": "&lt;span class=\"display-none mobile-lg:display-block text-uppercase\"&gt;U.S. Department of Agriculture&lt;/span&gt;",
              "xpath": "/html/body/div[1]/header[1]/div[1]/div[1]/div[1]/div[2]/a[2]/span[2]",
              "issueID": "702c2d8a547b0aef8e49a05be2b18ae4",
              "signature": "a65829b823f453792df2f259e03a2da1",
              "ref": "https://tenon.io/bestpractice.php?bpID=211&tID=153&issueID=702c2d8a547b0aef8e49a05be2b18ae4"
            },
            {
              "tID": 153,
              "bpID": 211,
              "priority": 85,
              "level": [
                "A",
                "AA",
                "AAA"
              ],
              "certainty": 60,
              "errorTitle": "This long string of text is in all caps.",
              "standards": [
                "Web Content Accessibility Guidelines (WCAG) 2.0, Level A: 1.3.1 Info and Relationships",
                "Web Content Accessibility Guidelines (WCAG) 2.0, Level AA: 1.4.5 Images of Text",
                "Web Content Accessibility Guidelines (WCAG) 2.0, Level AA: 3.2.4 Consistent Identification",
                "Web Content Accessibility Guidelines (WCAG) 2.0, Level AA: 1.4.4 Resize text",
                "Web Content Accessibility Guidelines (WCAG) 2.0, Level AAA: 2.5.5 Target Size"
              ],
              "resultTitle": "Ensure content is legible.",
              "errorDescription": "This element contains a long passage of text that is capitalized, either in the text itself or via CSS text-transform.  Capitalized text can be very difficult to read for users with dyslexia Modify this passage of text so that it is no longer all in upper case. Changing this to sentence case will result in significant improvements in readability.",
              "viewPortLocation": {
                "top-left": {
                  "x": 161.515625,
                  "y": 29
                },
                "bottom-right": {
                  "x": 458.515625,
                  "y": 49
                },
                "height": 20,
                "width": 297
              },
              "position": {
                "line": 9479,
                "column": 7
              },
              "errorSnippet": "&lt;span class=\"display-none mobile-lg:display-block text-uppercase\"&gt;U.S. Department of Agriculture&lt;/span&gt;",
              "xpath": "/html/body/div[1]/footer[1]/div[3]/div[1]/div[1]/div[1]/div[1]/div[2]/a[2]/span[2]",
              "issueID": "bfc1f2a54f7cc36211c54399f8508400",
              "signature": "a71490165f1000da72d91d98fffa6fe8",
              "ref": "https://tenon.io/bestpractice.php?bpID=211&tID=153&issueID=bfc1f2a54f7cc36211c54399f8508400"
            },
            {
              "tID": 155,
              "bpID": 143,
              "priority": 100,
              "level": [
                "A",
                "AAA"
              ],
              "certainty": 60,
              "errorTitle": "These headings are not structured in a hierarchical manner.",
              "standards": [
                "Web Content Accessibility Guidelines (WCAG) 2.0, Level A: 1.3.1 Info and Relationships",
                "Web Content Accessibility Guidelines (WCAG) 2.0, Level AAA: 2.4.10 Section Headings"
              ],
              "resultTitle": "Make sure that headings are in the right order for the content.",
              "errorDescription": "The heading structure of this page does not effectively communicate the structure of the content on it. Heading elements provide important benefits: they act as wayfinding cues for in-page navigation, they contribute to page content summaries, and they provide context to the content below them. To do so effectively, headings should follow the `<h1>` to `<h6>` hierarchy and they should not skip levels. Restructure the document's heading order so it uses a clear, ordered, and intuitive hierarchy. Ensure there are no gaps between each numbered heading level and the next.",
              "viewPortLocation": {
                "top-left": {
                  "x": 0,
                  "y": 0
                },
                "bottom-right": {
                  "x": 1024,
                  "y": 2829.08
                },
                "height": 2829.08,
                "width": 1024
              },
              "position": {
                "line": 2169,
                "column": 60
              },
              "errorSnippet": "&lt;body data-once=\"b-root\"&gt;\n&lt;a href=\"#main-content\" class=\"usa-sr-only focusable\" data-kmt=\"1\"&gt; Skip to main content\n&lt;/a&gt; &lt;div class=\"dialog-off-canvas-main-canvas\" data-off-canvas-main-canvas=\"\"&gt; &lt;section class=\"usa-banner\"&gt; ",
              "xpath": "/html/body",
              "issueID": "067fa15d0c4c370a93617c37c89c8a8e",
              "signature": "cff231ea740a8aef8075a026f9aaacd1",
              "ref": "https://tenon.io/bestpractice.php?bpID=143&tID=155&issueID=067fa15d0c4c370a93617c37c89c8a8e"
            },
            {
              "tID": 190,
              "bpID": 73,
              "priority": 100,
              "level": [
                "A",
                "AAA"
              ],
              "certainty": 100,
              "errorTitle": "Item(s) with interactive `role` must have `tabindex=\"0\"` unless it is natively actionable.",
              "standards": [
                "Web Content Accessibility Guidelines (WCAG) 2.0, Level A: 2.1.1 Keyboard",
                "Web Content Accessibility Guidelines (WCAG) 2.0, Level AAA: 2.1.3 Keyboard (No Exception)"
              ],
              "resultTitle": "Make sure that all interactive elements can receive focus using the keyboard.",
              "errorDescription": "This element has an ARIA role that is intended for widgets that are used for interaction. However, it lacks a `tabindex` attribute.  As a consequence, users who navigate the page via keyboard will be unable to gain focus on this control and will be unable to interact with it with the keyboard. Add `tabindex=\"0\"` to this control. Also ensure that this control responds to all of the necessary key events required of this type of control.",
              "viewPortLocation": {
                "top-left": {
                  "x": 0,
                  "y": 24
                },
                "bottom-right": {
                  "x": 320,
                  "y": 32
                },
                "height": 8,
                "width": 320
              },
              "position": {
                "line": 7952,
                "column": 11
              },
              "errorSnippet": "&lt;ul class=\"slick-dots\" style=\"\" role=\"tablist\"&gt;&lt;li class=\"\" role=\"presentation\"&gt;&lt;button type=\"button\" role=\"tab\" id=\"slick-slide-control00\" aria-controls=\"slick-slide00\" aria-label=\"1 of 5\" tabindex=\"-1\"&gt;1&lt;/button&gt;&lt;/li&gt;&lt;l",
              "xpath": "/html/body/div[1]/main[1]/div[3]/article[1]/div[1]/div[1]/div[1]/div[1]/div[1]/div[1]/div[1]/div[1]/ul[1]",
              "issueID": "86f1e7c72582becb5e0b527b6950927e",
              "signature": "706a54dba5fe33f78fe5820d748ddaad",
              "ref": "https://tenon.io/bestpractice.php?bpID=73&tID=190&issueID=86f1e7c72582becb5e0b527b6950927e"
            },
            {
              "tID": 218,
              "bpID": 207,
              "priority": 88,
              "level": [
                "AAA"
              ],
              "certainty": 100,
              "errorTitle": "This link opens in a new window without user control.",
              "standards": [
                "Web Content Accessibility Guidelines (WCAG) 2.0, Level AAA: 3.2.5 Change on Request"
              ],
              "resultTitle": "Notify the user when links will open new windows or tabs",
              "errorDescription": "This link opens in a new window without user control. Opening a new window or new tab unexpectedly can cause confusion for users, particularly for blind users and those with low vision, cogntive impairments or learning disabilities.. Avoid opening links in new windows or tabs. If it is unavoidable, give the user warning via text or a properly marked up and appropriate icon.",
              "viewPortLocation": {
                "top-left": {
                  "x": 0,
                  "y": 0
                },
                "bottom-right": {
                  "x": 0,
                  "y": 0
                },
                "height": 0,
                "width": 0
              },
              "position": {
                "line": 6459,
                "column": 34
              },
              "errorSnippet": "&lt;a href=\"https://www.nationalforests.org/our-forests/national-forest-week\" target=\"_blank\" rel=\"noopener\" tabindex=\"-1\" data-kmt=\"1\"&gt; &lt;div class=\"text-center\"&gt; &lt;div&gt;&lt;strong&gt; &lt;picture&gt; &lt;source srcset=\"/sites/default/files/",
              "xpath": "/html/body/div[1]/main[1]/div[3]/article[1]/div[1]/div[1]/div[1]/div[1]/div[1]/div[1]/div[1]/div[1]/div[1]/div[1]/div[1]/div[1]/div[1]/div[1]/a[1]",
              "issueID": "158d53a3e4cef32ee09d44a7354e98e2",
              "signature": "ebcc7400e18ee5999c47cff76b3ae421",
              "ref": "https://tenon.io/bestpractice.php?bpID=207&tID=218&issueID=158d53a3e4cef32ee09d44a7354e98e2"
            },
            {
              "tID": 218,
              "bpID": 207,
              "priority": 88,
              "level": [
                "AAA"
              ],
              "certainty": 100,
              "errorTitle": "This link opens in a new window without user control.",
              "standards": [
                "Web Content Accessibility Guidelines (WCAG) 2.0, Level AAA: 3.2.5 Change on Request"
              ],
              "resultTitle": "Notify the user when links will open new windows or tabs",
              "errorDescription": "This link opens in a new window without user control. Opening a new window or new tab unexpectedly can cause confusion for users, particularly for blind users and those with low vision, cogntive impairments or learning disabilities.. Avoid opening links in new windows or tabs. If it is unavoidable, give the user warning via text or a properly marked up and appropriate icon.",
              "viewPortLocation": {
                "top-left": {
                  "x": 12,
                  "y": 0
                },
                "bottom-right": {
                  "x": 44,
                  "y": 32
                },
                "height": 32,
                "width": 32
              },
              "position": {
                "line": 8366,
                "column": 17
              },
              "errorSnippet": "&lt;a class=\"fs-social-link fs-social-link--twitter\" href=\"https://twitter.com/forestservice\" target=\"_blank\" rel=\"noopener\" data-kmt=\"1\"&gt; &lt;span&gt;Twitter&lt;/span&gt; &lt;/a&gt;",
              "xpath": "/html/body/div[1]/footer[1]/div[3]/div[1]/div[1]/div[2]/div[1]/div[1]/a[1]",
              "issueID": "01af59c5407ce89dab5a4853ce447f3b",
              "signature": "156fdd624b25cec847ea4d6c863ae0a4",
              "ref": "https://tenon.io/bestpractice.php?bpID=207&tID=218&issueID=01af59c5407ce89dab5a4853ce447f3b"
            },
            {
              "tID": 218,
              "bpID": 207,
              "priority": 88,
              "level": [
                "AAA"
              ],
              "certainty": 100,
              "errorTitle": "This link opens in a new window without user control.",
              "standards": [
                "Web Content Accessibility Guidelines (WCAG) 2.0, Level AAA: 3.2.5 Change on Request"
              ],
              "resultTitle": "Notify the user when links will open new windows or tabs",
              "errorDescription": "This link opens in a new window without user control. Opening a new window or new tab unexpectedly can cause confusion for users, particularly for blind users and those with low vision, cogntive impairments or learning disabilities.. Avoid opening links in new windows or tabs. If it is unavoidable, give the user warning via text or a properly marked up and appropriate icon.",
              "viewPortLocation": {
                "top-left": {
                  "x": 12,
                  "y": 0
                },
                "bottom-right": {
                  "x": 44,
                  "y": 32
                },
                "height": 32,
                "width": 32
              },
              "position": {
                "line": 8378,
                "column": 17
              },
              "errorSnippet": "&lt;a class=\"fs-social-link fs-social-link--facebook\" href=\"https://www.facebook.com/USForestService\" target=\"_blank\" rel=\"noopener\" data-kmt=\"1\"&gt; &lt;span&gt;Facebook&lt;/span&gt; &lt;/a&gt;",
              "xpath": "/html/body/div[1]/footer[1]/div[3]/div[1]/div[1]/div[2]/div[1]/div[2]/a[1]",
              "issueID": "d938b047b54da494a920ed43f99d69c2",
              "signature": "d41120ffe5f1bd5161db54460a483a15",
              "ref": "https://tenon.io/bestpractice.php?bpID=207&tID=218&issueID=d938b047b54da494a920ed43f99d69c2"
            },
            {
              "tID": 218,
              "bpID": 207,
              "priority": 88,
              "level": [
                "AAA"
              ],
              "certainty": 100,
              "errorTitle": "This link opens in a new window without user control.",
              "standards": [
                "Web Content Accessibility Guidelines (WCAG) 2.0, Level AAA: 3.2.5 Change on Request"
              ],
              "resultTitle": "Notify the user when links will open new windows or tabs",
              "errorDescription": "This link opens in a new window without user control. Opening a new window or new tab unexpectedly can cause confusion for users, particularly for blind users and those with low vision, cogntive impairments or learning disabilities.. Avoid opening links in new windows or tabs. If it is unavoidable, give the user warning via text or a properly marked up and appropriate icon.",
              "viewPortLocation": {
                "top-left": {
                  "x": 12,
                  "y": 0
                },
                "bottom-right": {
                  "x": 44,
                  "y": 32
                },
                "height": 32,
                "width": 32
              },
              "position": {
                "line": 8390,
                "column": 17
              },
              "errorSnippet": "&lt;a class=\"fs-social-link fs-social-link--youtube\" href=\"https://www.youtube.com/user/usdaForestService\" target=\"_blank\" rel=\"noopener\" data-kmt=\"1\"&gt; &lt;span&gt;Youtube&lt;/span&gt; &lt;/a&gt;",
              "xpath": "/html/body/div[1]/footer[1]/div[3]/div[1]/div[1]/div[2]/div[1]/div[3]/a[1]",
              "issueID": "a354f40ef7947efc0e8863c0432d411a",
              "signature": "5b9fd2c49060e842c225ac3f6cad10d8",
              "ref": "https://tenon.io/bestpractice.php?bpID=207&tID=218&issueID=a354f40ef7947efc0e8863c0432d411a"
            },
            {
              "tID": 218,
              "bpID": 207,
              "priority": 88,
              "level": [
                "AAA"
              ],
              "certainty": 100,
              "errorTitle": "This link opens in a new window without user control.",
              "standards": [
                "Web Content Accessibility Guidelines (WCAG) 2.0, Level AAA: 3.2.5 Change on Request"
              ],
              "resultTitle": "Notify the user when links will open new windows or tabs",
              "errorDescription": "This link opens in a new window without user control. Opening a new window or new tab unexpectedly can cause confusion for users, particularly for blind users and those with low vision, cogntive impairments or learning disabilities.. Avoid opening links in new windows or tabs. If it is unavoidable, give the user warning via text or a properly marked up and appropriate icon.",
              "viewPortLocation": {
                "top-left": {
                  "x": 12,
                  "y": 0
                },
                "bottom-right": {
                  "x": 44,
                  "y": 32
                },
                "height": 32,
                "width": 32
              },
              "position": {
                "line": 8402,
                "column": 17
              },
              "errorSnippet": "&lt;a class=\"fs-social-link fs-social-link--flickr\" href=\"https://www.flickr.com/photos/usforestservice/\" target=\"_blank\" rel=\"noopener\" data-kmt=\"1\"&gt; &lt;span&gt;Flickr&lt;/span&gt; &lt;/a&gt;",
              "xpath": "/html/body/div[1]/footer[1]/div[3]/div[1]/div[1]/div[2]/div[1]/div[4]/a[1]",
              "issueID": "099b17cdde4795d59897f76104c638ca",
              "signature": "dc5ee5db83f3998bdcdfe9d2c3789670",
              "ref": "https://tenon.io/bestpractice.php?bpID=207&tID=218&issueID=099b17cdde4795d59897f76104c638ca"
            },
            {
              "tID": 218,
              "bpID": 207,
              "priority": 88,
              "level": [
                "AAA"
              ],
              "certainty": 100,
              "errorTitle": "This link opens in a new window without user control.",
              "standards": [
                "Web Content Accessibility Guidelines (WCAG) 2.0, Level AAA: 3.2.5 Change on Request"
              ],
              "resultTitle": "Notify the user when links will open new windows or tabs",
              "errorDescription": "This link opens in a new window without user control. Opening a new window or new tab unexpectedly can cause confusion for users, particularly for blind users and those with low vision, cogntive impairments or learning disabilities.. Avoid opening links in new windows or tabs. If it is unavoidable, give the user warning via text or a properly marked up and appropriate icon.",
              "viewPortLocation": {
                "top-left": {
                  "x": 12,
                  "y": 0
                },
                "bottom-right": {
                  "x": 44,
                  "y": 32
                },
                "height": 32,
                "width": 32
              },
              "position": {
                "line": 8414,
                "column": 17
              },
              "errorSnippet": "&lt;a class=\"fs-social-link fs-social-link--instagram\" href=\"https://www.instagram.com/u.s.forestservice/\" target=\"_blank\" rel=\"noopener\" data-kmt=\"1\"&gt; &lt;span&gt;Instagram&lt;/span&gt; &lt;/a&gt;",
              "xpath": "/html/body/div[1]/footer[1]/div[3]/div[1]/div[1]/div[2]/div[1]/div[5]/a[1]",
              "issueID": "f874bec65893bd69cd7be14c29adb039",
              "signature": "8c8e9ae4fcb9198c280d30f73fa6fb8f",
              "ref": "https://tenon.io/bestpractice.php?bpID=207&tID=218&issueID=f874bec65893bd69cd7be14c29adb039"
            }
          ],
          "log": []
        }
      }
    }
  ],
  "timeStamp": "4cg53",
  "startTime": "2022-07-19T23:08:30",
  "presses": 0,
  "amountRead": 0,
  "testTimes": [
    [
      "tenon",
      7
    ],
    [
      "menuNav",
      0
    ]
  ],
  "logCount": 6,
  "logSize": 778,
  "errorLogCount": 6,
  "errorLogSize": 778,
  "prohibitedCount": 0,
  "visitTimeoutCount": 0,
  "visitRejectionCount": 0,
  "endTime": "2022-07-19T23:08:59",
  "elapsedSeconds": 28
}