{
  "id": "4jil2-bjs",
  "host": {
    "id": "bjs",
    "which": "https://bjs.gov/",
    "what": "Bureau of Justice Statistics"
  },
  "log": [
    {
      "event": "startTime",
      "value": "2022-07-27T14:40:22"
    },
    {
      "event": "endTime",
      "value": "2022-07-27T14:40:35"
    }
  ],
  "script": {
    "id": "continuum",
    "what": "Continuum",
    "strict": true,
    "timeLimit": 30,
    "commands": [
      {
        "type": "launch",
        "which": "chromium",
        "what": "Chromium browser"
      },
      {
        "type": "url",
        "which": "https://bjs.gov/",
        "what": "Bureau of Justice Statistics"
      },
      {
        "type": "test",
        "which": "continuum",
        "what": "Continuum"
      }
    ]
  },
  "acts": [
    {
      "type": "launch",
      "which": "chromium",
      "what": "Chromium browser"
    },
    {
      "type": "url",
      "which": "https://bjs.gov/",
      "what": "Bureau of Justice Statistics",
      "result": "https://bjs.ojp.gov/"
    },
    {
      "type": "test",
      "which": "continuum",
      "what": "Level Access Continuum, community edition",
      "url": "https://bjs.ojp.gov/",
      "result": [
        {
          "engineTestId": 224,
          "bestPracticeId": 338,
          "attribute": "This button element does not have a mechanism that allows an accessible name value to be calculated",
          "attributeDetail": "This button element does not have a mechanism that allows an accessible name value to be calculated",
          "element": "<button class=\"gsc-search-button gsc-search-button-v2\"><svg viewbox=\"0 0 13 13\" height=\"13\" width=\"1 ... .0924 1.3909 3.4239 0 1.2126-0.38043 2.2588-1.1413 3.1385l0.098834 0.090049z\"></path></svg></button>",
          "testResult": 0,
          "path": "body>div:nth-of-type(1)>*:nth-child(2)>*:nth-child(3)>*:nth-child(1)>*:nth-child(3)>*:nth-child(1)>*:nth-child(1)>*:nth-child(1)>*:nth-child(1)>*:nth-child(1)>*:nth-child(1)>*:nth-child(1)>*:nth-child(1)>*:nth-child(1)>*:nth-child(2)>*:nth-child(1)",
          "fixType": "",
          "fingerprint": {
            "version": 2,
            "css": "button[class=\"gsc-search-button gsc-search-button-v2\"]",
            "attNo": 1
          }
        }
      ]
    }
  ],
  "timeStamp": "4jil2",
  "startTime": "2022-07-27T14:40:22",
  "presses": 0,
  "amountRead": 0,
  "testTimes": [
    [
      "continuum",
      0
    ]
  ],
  "logCount": 5,
  "logSize": 715,
  "errorLogCount": 4,
  "errorLogSize": 685,
  "prohibitedCount": 0,
  "visitTimeoutCount": 0,
  "visitRejectionCount": 0,
  "endTime": "2022-07-27T14:40:35",
  "elapsedSeconds": 12
}